FlaskEchoIP/__init__.py
FlaskEchoIP-2.0.0.dist-info/LICENSE
FlaskEchoIP-2.0.0.dist-info/METADATA
FlaskEchoIP-2.0.0.dist-info/WHEEL
FlaskEchoIP-2.0.0.dist-info/top_level.txt
FlaskEchoIP-2.0.0.dist-info/RECORD
