Metadata-Version: 2.1
Name: FlaskEchoIP
Version: 2.0.0
Summary: A simple Flask app that returns the value of the `X-Forwarded-For` header
License:                     GNU GENERAL PUBLIC LICENSE
Project-URL: Homepage, https://github.com/jb2170/FlaskEchoIP/
License-File: LICENSE
Requires-Dist: Flask
